Workbook
Name area_sqft: Inputs!$C$6
Name area_sqft_low: Inputs!$F$6
Name area_sqft_high: Inputs!$G$6
Name mature_sales_density: Inputs!$C$7
Name mature_sales_density_low: Inputs!$F$7
Name mature_sales_density_high: Inputs!$G$7
Name ramp_year1: Inputs!$C$8
Name ramp_year1_low: Inputs!$F$8
Name ramp_year1_high: Inputs!$G$8
Name ramp_year2: Inputs!$C$9
Name ramp_year2_low: Inputs!$F$9
Name ramp_year2_high: Inputs!$G$9
Name sales_growth: Inputs!$C$10
Name sales_growth_low: Inputs!$F$10
Name sales_growth_high: Inputs!$G$10
Name product_gross_margin: Inputs!$C$11
Name product_gross_margin_low: Inputs!$F$11
Name product_gross_margin_high: Inputs!$G$11
Name rent_per_year: Inputs!$C$12
Name rent_per_year_low: Inputs!$F$12
Name rent_per_year_high: Inputs!$G$12
Name rent_review_uplift: Inputs!$C$13
Name rent_review_uplift_low: Inputs!$F$13
Name rent_review_uplift_high: Inputs!$G$13
Name occupancy_other_psf: Inputs!$C$14
Name occupancy_other_psf_low: Inputs!$F$14
Name occupancy_other_psf_high: Inputs!$G$14
Name rateable_value: Inputs!$C$15
Name rateable_value_low: Inputs!$F$15
Name rateable_value_high: Inputs!$G$15
Name other_opex_pct_sales: Inputs!$C$16
Name other_opex_pct_sales_low: Inputs!$F$16
Name other_opex_pct_sales_high: Inputs!$G$16
Name fitout_capex: Inputs!$C$17
Name fitout_capex_low: Inputs!$F$17
Name fitout_capex_high: Inputs!$G$17
Name pre_opening_costs: Inputs!$C$18
Name pre_opening_costs_low: Inputs!$F$18
Name pre_opening_costs_high: Inputs!$G$18
Name stock_pct_sales: Inputs!$C$19
Name stock_pct_sales_low: Inputs!$F$19
Name stock_pct_sales_high: Inputs!$G$19
Name dilapidations_at_exit: Inputs!$C$20
Name dilapidations_at_exit_low: Inputs!$F$20
Name dilapidations_at_exit_high: Inputs!$G$20
Name lease_term_years: Inputs!$C$21
Name lease_term_years_low: Inputs!$F$21
Name lease_term_years_high: Inputs!$G$21
Name discount_rate: Inputs!$C$22
Name discount_rate_low: Inputs!$F$22
Name discount_rate_high: Inputs!$G$22
Name tax_rate: Inputs!$C$23
Name tax_rate_low: Inputs!$F$23
Name tax_rate_high: Inputs!$G$23
Name tax_depreciation_years: Inputs!$C$24
Name tax_depreciation_years_low: Inputs!$F$24
Name tax_depreciation_years_high: Inputs!$G$24
Name wage_inflation: Inputs!$C$25
Name wage_inflation_low: Inputs!$F$25
Name wage_inflation_high: Inputs!$G$25

Sheet Inputs
A1: New-store appraisal: inputs
A2: Illustrative and assumption-driven. Mint Velvet store-level data is not public; outputs are not Mint Velvet's store economics. Independent analysis of public filings, not affiliated with or endorsed by Mint Velvet or Sabre Retail Fashion Limited.
A3: Blue = input. Basis: SOURCED (public source), FILING_PROXY (derived from the filed accounts; capex, rent and stock proxies are upper bounds), ASSUMPTION (analyst assumption).
A5: Section | B5: Input | C5: Value | D5: Unit | E5: Basis | F5: Low | G5: High | H5: Source / derivation
A6: store | B6: area_sqft | C6: 1700 | D6: sq ft | E6: SOURCED | F6: 1700 | G6: 1700 | H6: Store size in the July 2026 Meadowhall signing announcement (TheIndustry.fashion, 29 Jul 2026): https://www.theindustry.fashion/meadowhall-strengthens-fashion-line-up-with-mint-velvet-belstaff-and-michael-kors-deals/
A7: store | B7: mature_sales_density | C7: 850 | D7: GBP per sq ft per year (year-1 prices) | E7: ASSUMPTION | F7: 600 | G7: 1100 | H7: No public store-level sales. The model solves for the break-even density, which does not depend on this input; the base value only sets the illustrative NPV.
A8: store | B8: ramp_year1 | C8: 0.8 | D8: share of mature sales | E8: ASSUMPTION | F8: 0.7 | G8: 0.9 | H8: New-store sales build; year 3 onwards = 100%.
A9: store | B9: ramp_year2 | C9: 0.95 | D9: share of mature sales | E9: ASSUMPTION | F9: 0.9 | G9: 1 | H9: New-store sales build.
A10: store | B10: sales_growth | C10: 0.02 | D10: per year, nominal, from year 2 | E10: ASSUMPTION | F10: 0 | G10: 0.04 | H10: Like-for-like price/mix growth on the matured base.
A11: store | B11: product_gross_margin | C11: 0.7102 | D11: share of sales | E11: FILING_PROXY | F11: 0.66 | G11: 0.74 | H11: FY22 accounts note 6 (pdf p.34): 1 - cost of stock expensed 41,639 / turnover 143,675. The only year the filings disclose cost of stock; company-wide (all channels, after markdowns). low/high are ASSUMPTION (+/-4.5pp).
A12: store | B12: rent_per_year | C12: 95340 | D12: GBP per year | E12: FILING_PROXY | F12: 70000 | G12: 200000 | H12: FY25 accounts: operating lease rentals 5,053k (note 6, pdf p.33) / 53 standalone stores (strategic report, pdf p.4). Upper bound for an average store: includes head office and any other leased property. low/high are ASSUMPTION; a super-regional mall unit can cost well above the estate average, so high is about 2x the proxy.
A13: store | B13: rent_review_uplift | C13: 0.1 | D13: one-off uplift at year 6 (five-yearly review) | E13: ASSUMPTION | F13: 0 | G13: 0.2 | H13: Upward-only review at year 5 anniversary.
A14: store | B14: occupancy_other_psf | C14: 15 | D14: GBP per sq ft per year | E14: ASSUMPTION | F14: 8 | G14: 25 | H14: Service charge, insurance, utilities. Indexed at cost_inflation.
A15: store | B15: rateable_value | C15: 55000 | D15: GBP | E15: ASSUMPTION | F15: 40000 | G15: 90000 | H15: Replace with the unit's entry on the VOA 2026 rating list. Rates = RV x the 2026/27 RHL multiplier for its band (payroll_and_tax section).
A16: store | B16: other_opex_pct_sales | C16: 0.1 | D16: share of sales | E16: ASSUMPTION | F16: 0.06 | G16: 0.15 | H16: Allowance for distribution to store, shrinkage, card fees, store marketing, repairs, cleaning, security and store systems. Not a benchmark. The filings put all retail-channel costs other than staff, rent and D&A in one pool (bridge 'other operating costs'), which cannot be split to store level.
A17: store | B17: fitout_capex | C17: 528000 | D17: GBP at opening | E17: FILING_PROXY | F17: 323333 | G17: 931500 | H17: FY24 accounts: tangible additions 2,640k (note 14, pdf p.37) / 5 projects (3 openings + 2 relocations, pdf p.4). Upper bound: additions also include refits, IT and head-office capex. low = FY22 (1,940k / 6 openings), high = FY23 (3,726k / 4 openings).
... A50: payroll_and_tax | B50: rates_multiplier_high_value | C50: 0.508 | D50: GBP per GBP of RV, all properties RV 500,000+, 2026/27 | E50: SOURCED | F50: 0.508 | G50: 0.508 | H50: England 2026/27 multipliers, e.g. https://www.spelthorne.gov.uk/page/661/business-rates-multipliers-20262027

Sheet Payroll
A1: Bottom-up store payroll (year-1 prices, 2026/27 statutory rates)
A2: Associates: part-time contracts at NLW plus premium; managers salaried. Fixed hours cover the floor across trading hours; variable hours scale with sales volume.
A4: Item | B4: Description | C4: Value
A5: holiday_uplift | B5: Holiday pay uplift per hour worked | C5: =holiday_weeks/(52-holiday_weeks)
A6: assoc_rate | B6: Associate hourly rate | C6: =nlw_hourly*(1+associate_premium_over_nlw)
A7: assoc_earnings | B7: Associate annual earnings (incl. holiday pay) | C7: =associate_contract_hours_per_week*52*assoc_rate*(1+holiday_uplift)
A8: assoc_nic | B8: Employer NIC per associate, 2026/27 | C8: =employer_nic_rate*MAX(0,assoc_earnings-nic_secondary_threshold)
A9: assoc_nic_old | B9: Employer NIC per associate under 2024/25 rules (comparison) | C9: =employer_nic_rate_2024_25*MAX(0,assoc_earnings-nic_secondary_threshold_2024_25)
A10: assoc_nic_increase | B10: Increase in employer NIC per associate | C10: =assoc_nic/assoc_nic_old-1
A11: assoc_pension | B11: Employer pension per associate | C11: =IF(assoc_earnings<pension_trigger,0,pension_employer_rate*MAX(0,MIN(assoc_earnings,pension_qe_upper)-pension_qe_lower))
A12: assoc_cost_per_hour | B12: Associate cost per hour worked (pay, holiday, NIC, pension) | C12: =(assoc_earnings+assoc_nic+assoc_pension)/(associate_contract_hours_per_week*52)
A13: sm_cost | B13: Store manager total cost | C13: =store_manager_salary+employer_nic_rate*MAX(0,store_manager_salary-nic_secondary_threshold)+IF(store_manager_salary<pension_trigger,0,pension_employer_rate*MAX(0,MIN(store_manager_salary,pension_qe_upper)-pension_qe_lower))
A14: am_cost | B14: Assistant manager total cost | C14: =assistant_manager_salary+employer_nic_rate*MAX(0,assistant_manager_salary-nic_secondary_threshold)+IF(assistant_manager_salary<pension_trigger,0,pension_employer_rate*MAX(0,MIN(assistant_manager_salary,pension_qe_upper)-pension_qe_lower))
A15: managers_cost | B15: Managers total cost | C15: =IF(managers>=1,sm_cost,0)+IF(managers>=2,am_cost,0)
A16: fixed_assoc_hours_week | B16: Fixed associate hours per week | C16: =MAX(0,trading_hours_per_week*floor_cover+non_trading_hours_per_week-managers*manager_floor_hours_per_week)
A17: fixed_payroll | B17: Fixed payroll per year | C17: =managers_cost+fixed_assoc_hours_week*52*assoc_cost_per_hour
A18: variable_cost_per_k | B18: Variable payroll per GBP 1,000 of sales volume | C18: =variable_hours_per_k_sales*assoc_cost_per_hour

Sheet Store P&L
A1: Base case: store 4-wall P&L and cash flow (GBP, nominal)
A2: Illustrative and assumption-driven. Mint Velvet store-level data is not public; outputs are not Mint Velvet's store economics. Independent analysis of public filings, not affiliated with or endorsed by Mint Velvet or Sabre Retail Fashion Limited.
A4: Base case
A5: param: density | B5: =mature_sales_density
A6: param: gm | B6: =product_gross_margin
A7: param: rent | B7: =rent_per_year
A8: param: capex | B8: =fitout_capex
A9: param: ramp1 | B9: =ramp_year1
A10: param: ramp2 | B10: =ramp_year2
A11: param: rent_mult | B11: 1
A12: param: payroll_mult | B12: 1
A13: param: ramp_mult | B13: 1
A15: Year | C15: 0 | D15: 1 | E15: 2 | F15: 3 | G15: 4 | H15: 5 | I15: 6 | J15: 7 | K15: 8 | L15: 9 | M15: 10 | N15: 11 | O15: 12 | P15: 13 | Q15: 14 | R15: 15
A16: Trading year flag | C16: =IF(AND(C15>=1,C15<=lease_term_years),1,0) | D16: =IF(AND(D15>=1,D15<=lease_term_years),1,0) | E16: =IF(AND(E15>=1,E15<=lease_term_years),1,0) | F16: =IF(AND(F15>=1,F15<=lease_term_years),1,0) | G16: =IF(AND(G15>=1,G15<=lease_term_years),1,0) | H16: =IF(AND(H15>=1,H15<=lease_term_years),1,0) | I16: =IF(AND(I15>=1,I15<=lease_term_years),1,0) | J16: =IF(AND(J15>=1,J15<=lease_term_years),1,0) | ... R16: =IF(AND(R15>=1,R15<=lease_term_years),1,0)
A17: Ramp-up (share of mature volume) | C17: =IF(C15=1,1-(1-$B$9)*$B$13,IF(C15=2,1-(1-$B$10)*$B$13,1))*C16 | D17: =IF(D15=1,1-(1-$B$9)*$B$13,IF(D15=2,1-(1-$B$10)*$B$13,1))*D16 | E17: =IF(E15=1,1-(1-$B$9)*$B$13,IF(E15=2,1-(1-$B$10)*$B$13,1))*E16 | F17: =IF(F15=1,1-(1-$B$9)*$B$13,IF(F15=2,1-(1-$B$10)*$B$13,1))*F16 | G17: =IF(G15=1,1-(1-$B$9)*$B$13,IF(G15=2,1-(1-$B$10)*$B$13,1))*G16 | H17: =IF(H15=1,1-(1-$B$9)*$B$13,IF(H15=2,1-(1-$B$10)*$B$13,1))*H16 | I17: =IF(I15=1,1-(1-$B$9)*$B$13,IF(I15=2,1-(1-$B$10)*$B$13,1))*I16 | J17: =IF(J15=1,1-(1-$B$9)*$B$13,IF(J15=2,1-(1-$B$10)*$B$13,1))*J16 | ... R17: =IF(R15=1,1-(1-$B$9)*$B$13,IF(R15=2,1-(1-$B$10)*$B$13,1))*R16
A18: Sales volume (year-1 prices) | C18: =area_sqft*$B$5*C17 | D18: =area_sqft*$B$5*D17 | E18: =area_sqft*$B$5*E17 | F18: =area_sqft*$B$5*F17 | G18: =area_sqft*$B$5*G17 | H18: =area_sqft*$B$5*H17 | I18: =area_sqft*$B$5*I17 | J18: =area_sqft*$B$5*J17 | ... R18: =area_sqft*$B$5*R17
A19: Sales growth index | C19: =IF(C16=1,(1+sales_growth)^(C15-1),0) | D19: =IF(D16=1,(1+sales_growth)^(D15-1),0) | E19: =IF(E16=1,(1+sales_growth)^(E15-1),0) | F19: =IF(F16=1,(1+sales_growth)^(F15-1),0) | G19: =IF(G16=1,(1+sales_growth)^(G15-1),0) | H19: =IF(H16=1,(1+sales_growth)^(H15-1),0) | I19: =IF(I16=1,(1+sales_growth)^(I15-1),0) | J19: =IF(J16=1,(1+sales_growth)^(J15-1),0) | ... R19: =IF(R16=1,(1+sales_growth)^(R15-1),0)
A20: Sales | C20: =C18*C19 | D20: =D18*D19 | E20: =E18*E19 | F20: =F18*F19 | G20: =G18*G19 | H20: =H18*H19 | I20: =I18*I19 | J20: =J18*J19 | ... R20: =R18*R19
A21: Gross margin | C21: =C20*$B$6 | D21: =D20*$B$6 | E21: =E20*$B$6 | F21: =F20*$B$6 | G21: =G20*$B$6 | H21: =H20*$B$6 | I21: =I20*$B$6 | J21: =J20*$B$6 | ... R21: =R20*$B$6
A22: Wage index | C22: =IF(C16=1,(1+wage_inflation)^(C15-1),0) | D22: =IF(D16=1,(1+wage_inflation)^(D15-1),0) | E22: =IF(E16=1,(1+wage_inflation)^(E15-1),0) | F22: =IF(F16=1,(1+wage_inflation)^(F15-1),0) | G22: =IF(G16=1,(1+wage_inflation)^(G15-1),0) | H22: =IF(H16=1,(1+wage_inflation)^(H15-1),0) | I22: =IF(I16=1,(1+wage_inflation)^(I15-1),0) | J22: =IF(J16=1,(1+wage_inflation)^(J15-1),0) | ... R22: =IF(R16=1,(1+wage_inflation)^(R15-1),0)
A23: Payroll | C23: =(fixed_payroll*C16+variable_cost_per_k*C18/1000)*C22*$B$12 | D23: =(fixed_payroll*D16+variable_cost_per_k*D18/1000)*D22*$B$12 | E23: =(fixed_payroll*E16+variable_cost_per_k*E18/1000)*E22*$B$12 | F23: =(fixed_payroll*F16+variable_cost_per_k*F18/1000)*F22*$B$12 | G23: =(fixed_payroll*G16+variable_cost_per_k*G18/1000)*G22*$B$12 | H23: =(fixed_payroll*H16+variable_cost_per_k*H18/1000)*H22*$B$12 | I23: =(fixed_payroll*I16+variable_cost_per_k*I18/1000)*I22*$B$12 | J23: =(fixed_payroll*J16+variable_cost_per_k*J18/1000)*J22*$B$12 | ... R23: =(fixed_payroll*R16+variable_cost_per_k*R18/1000)*R22*$B$12
A24: Rent | C24: =$B$7*(1+IF(C15>=6,rent_review_uplift,0))*C16*$B$11 | D24: =$B$7*(1+IF(D15>=6,rent_review_uplift,0))*D16*$B$11 | E24: =$B$7*(1+IF(E15>=6,rent_review_uplift,0))*E16*$B$11 | F24: =$B$7*(1+IF(F15>=6,rent_review_uplift,0))*F16*$B$11 | G24: =$B$7*(1+IF(G15>=6,rent_review_uplift,0))*G16*$B$11 | H24: =$B$7*(1+IF(H15>=6,rent_review_uplift,0))*H16*$B$11 | I24: =$B$7*(1+IF(I15>=6,rent_review_uplift,0))*I16*$B$11 | J24: =$B$7*(1+IF(J15>=6,rent_review_uplift,0))*J16*$B$11 | ... R24: =$B$7*(1+IF(R15>=6,rent_review_uplift,0))*R16*$B$11
A25: Cost index | C25: =IF(C16=1,(1+cost_inflation)^(C15-1),0) | D25: =IF(D16=1,(1+cost_inflation)^(D15-1),0) | E25: =IF(E16=1,(1+cost_inflation)^(E15-1),0) | F25: =IF(F16=1,(1+cost_inflation)^(F15-1),0) | G25: =IF(G16=1,(1+cost_inflation)^(G15-1),0) | H25: =IF(H16=1,(1+cost_inflation)^(H15-1),0) | I25: =IF(I16=1,(1+cost_inflation)^(I15-1),0) | J25: =IF(J16=1,(1+cost_inflation)^(J15-1),0) | ... R25: =IF(R16=1,(1+cost_inflation)^(R15-1),0)
A26: Business rates | C26: =rateable_value*IF(rateable_value<51000,rates_multiplier_rhl_small,IF(rateable_value<500000,rates_multiplier_rhl_standard,rates_multiplier_high_value))*C25 | D26: =rateable_value*IF(rateable_value<51000,rates_multiplier_rhl_small,IF(rateable_value<500000,rates_multiplier_rhl_standard,rates_multiplier_high_value))*D25 | E26: =rateable_value*IF(rateable_value<51000,rates_multiplier_rhl_small,IF(rateable_value<500000,rates_multiplier_rhl_standard,rates_multiplier_high_value))*E25 | F26: =rateable_value*IF(rateable_value<51000,rates_multiplier_rhl_small,IF(rateable_value<500000,rates_multiplier_rhl_standard,rates_multiplier_high_value))*F25 | G26: =rateable_value*IF(rateable_value<51000,rates_multiplier_rhl_small,IF(rateable_value<500000,rates_multiplier_rhl_standard,rates_multiplier_high_value))*G25 | H26: =rateable_value*IF(rateable_value<51000,rates_multiplier_rhl_small,IF(rateable_value<500000,rates_multiplier_rhl_standard,rates_multiplier_high_value))*H25 | I26: =rateable_value*IF(rateable_value<51000,rates_multiplier_rhl_small,IF(rateable_value<500000,rates_multiplier_rhl_standard,rates_multiplier_high_value))*I25 | J26: =rateable_value*IF(rateable_value<51000,rates_multiplier_rhl_small,IF(rateable_value<500000,rates_multiplier_rhl_standard,rates_multiplier_high_value))*J25 | ... R26: =rateable_value*IF(rateable_value<51000,rates_multiplier_rhl_small,IF(rateable_value<500000,rates_multiplier_rhl_standard,rates_multiplier_high_value))*R25
A27: Service charge, utilities, insurance | C27: =occupancy_other_psf*area_sqft*C25 | D27: =occupancy_other_psf*area_sqft*D25 | E27: =occupancy_other_psf*area_sqft*E25 | F27: =occupancy_other_psf*area_sqft*F25 | G27: =occupancy_other_psf*area_sqft*G25 | H27: =occupancy_other_psf*area_sqft*H25 | I27: =occupancy_other_psf*area_sqft*I25 | J27: =occupancy_other_psf*area_sqft*J25 | ... R27: =occupancy_other_psf*area_sqft*R25
A28: Other store opex | C28: =C20*other_opex_pct_sales | D28: =D20*other_opex_pct_sales | E28: =E20*other_opex_pct_sales | F28: =F20*other_opex_pct_sales | G28: =G20*other_opex_pct_sales | H28: =H20*other_opex_pct_sales | I28: =I20*other_opex_pct_sales | J28: =J20*other_opex_pct_sales | ... R28: =R20*other_opex_pct_sales
A29: Store EBITDA (4-wall) | C29: =C21-C23-C24-C26-C27-C28 | D29: =D21-D23-D24-D26-D27-D28 | E29: =E21-E23-E24-E26-E27-E28 | F29: =F21-F23-F24-F26-F27-F28 | G29: =G21-G23-G24-G26-G27-G28 | H29: =H21-H23-H24-H26-H27-H28 | I29: =I21-I23-I24-I26-I27-I28 | J29: =J21-J23-J24-J26-J27-J28 | ... R29: =R21-R23-R24-R26-R27-R28
A30: Pre-opening costs | C30: =IF(C15=0,pre_opening_costs,0) | D30: =IF(D15=0,pre_opening_costs,0) | E30: =IF(E15=0,pre_opening_costs,0) | F30: =IF(F15=0,pre_opening_costs,0) | G30: =IF(G15=0,pre_opening_costs,0) | H30: =IF(H15=0,pre_opening_costs,0) | I30: =IF(I15=0,pre_opening_costs,0) | J30: =IF(J15=0,pre_opening_costs,0) | ... R30: =IF(R15=0,pre_opening_costs,0)
A31: Fit-out capex | C31: =IF(C15=0,$B$8,0) | D31: =IF(D15=0,$B$8,0) | E31: =IF(E15=0,$B$8,0) | F31: =IF(F15=0,$B$8,0) | G31: =IF(G15=0,$B$8,0) | H31: =IF(H15=0,$B$8,0) | I31: =IF(I15=0,$B$8,0) | J31: =IF(J15=0,$B$8,0) | ... R31: =IF(R15=0,$B$8,0)
A32: Tax depreciation | C32: =IF(AND(C15>=1,C15<=tax_depreciation_years,C15<=lease_term_years),$B$8/tax_depreciation_years,0) | D32: =IF(AND(D15>=1,D15<=tax_depreciation_years,D15<=lease_term_years),$B$8/tax_depreciation_years,0) | E32: =IF(AND(E15>=1,E15<=tax_depreciation_years,E15<=lease_term_years),$B$8/tax_depreciation_years,0) | F32: =IF(AND(F15>=1,F15<=tax_depreciation_years,F15<=lease_term_years),$B$8/tax_depreciation_years,0) | G32: =IF(AND(G15>=1,G15<=tax_depreciation_years,G15<=lease_term_years),$B$8/tax_depreciation_years,0) | H32: =IF(AND(H15>=1,H15<=tax_depreciation_years,H15<=lease_term_years),$B$8/tax_depreciation_years,0) | I32: =IF(AND(I15>=1,I15<=tax_depreciation_years,I15<=lease_term_years),$B$8/tax_depreciation_years,0) | J32: =IF(AND(J15>=1,J15<=tax_depreciation_years,J15<=lease_term_years),$B$8/tax_depreciation_years,0) | ... R32: =IF(AND(R15>=1,R15<=tax_depreciation_years,R15<=lease_term_years),$B$8/tax_depreciation_years,0)
A33: Dilapidations | C33: =IF(C15=lease_term_years,dilapidations_at_exit,0) | D33: =IF(D15=lease_term_years,dilapidations_at_exit,0) | E33: =IF(E15=lease_term_years,dilapidations_at_exit,0) | F33: =IF(F15=lease_term_years,dilapidations_at_exit,0) | G33: =IF(G15=lease_term_years,dilapidations_at_exit,0) | H33: =IF(H15=lease_term_years,dilapidations_at_exit,0) | I33: =IF(I15=lease_term_years,dilapidations_at_exit,0) | J33: =IF(J15=lease_term_years,dilapidations_at_exit,0) | ... R33: =IF(R15=lease_term_years,dilapidations_at_exit,0)
A34: Taxable profit | C34: =C29-C30-C32-C33 | D34: =D29-D30-D32-D33 | E34: =E29-E30-E32-E33 | F34: =F29-F30-F32-F33 | G34: =G29-G30-G32-G33 | H34: =H29-H30-H32-H33 | I34: =I29-I30-I32-I33 | J34: =J29-J30-J32-J33 | ... R34: =R29-R30-R32-R33
A35: Tax (negative = group relief) | C35: =C34*tax_rate | D35: =D34*tax_rate | E35: =E34*tax_rate | F35: =F34*tax_rate | G35: =G34*tax_rate | H35: =H34*tax_rate | I35: =I34*tax_rate | J35: =J34*tax_rate | ... R35: =R34*tax_rate
A36: Stock held | C36: =IF(C15<lease_term_years,stock_pct_sales*D20,0) | D36: =IF(D15<lease_term_years,stock_pct_sales*E20,0) | E36: =IF(E15<lease_term_years,stock_pct_sales*F20,0) | F36: =IF(F15<lease_term_years,stock_pct_sales*G20,0) | G36: =IF(G15<lease_term_years,stock_pct_sales*H20,0) | H36: =IF(H15<lease_term_years,stock_pct_sales*I20,0) | I36: =IF(I15<lease_term_years,stock_pct_sales*J20,0) | J36: =IF(J15<lease_term_years,stock_pct_sales*K20,0) | ... Q36: =IF(Q15<lease_term_years,stock_pct_sales*R20,0) | R36: =0
A37: Change in stock | C37: =C36 | D37: =D36-C36 | E37: =E36-D36 | F37: =F36-E36 | G37: =G36-F36 | H37: =H36-G36 | I37: =I36-H36 | J37: =J36-I36 | K37: =K36-J36 | ... R37: =R36-Q36
A38: Free cash flow | C38: =C29-C30-C35-C31-C37-C33 | D38: =D29-D30-D35-D31-D37-D33 | E38: =E29-E30-E35-E31-E37-E33 | F38: =F29-F30-F35-F31-F37-F33 | G38: =G29-G30-G35-G31-G37-G33 | H38: =H29-H30-H35-H31-H37-H33 | I38: =I29-I30-I35-I31-I37-I33 | J38: =J29-J30-J35-J31-J37-J33 | ... R38: =R29-R30-R35-R31-R37-R33
A39: Discount factor | C39: =1/(1+discount_rate)^C15 | D39: =1/(1+discount_rate)^D15 | E39: =1/(1+discount_rate)^E15 | F39: =1/(1+discount_rate)^F15 | G39: =1/(1+discount_rate)^G15 | H39: =1/(1+discount_rate)^H15 | I39: =1/(1+discount_rate)^I15 | J39: =1/(1+discount_rate)^J15 | ... R39: =1/(1+discount_rate)^R15
A40: Present value | C40: =C38*C39 | D40: =D38*D39 | E40: =E38*E39 | F40: =F38*F39 | G40: =G38*G39 | H40: =H38*H39 | I40: =I38*I39 | J40: =J38*J39 | ... R40: =R38*R39
A41: Cumulative cash flow | C41: =C38 | D41: =C41+D38 | E41: =D41+E38 | F41: =E41+F38 | G41: =F41+G38 | H41: =G41+H38 | I41: =H41+I38 | J41: =I41+J38 | K41: =J41+K38 | ... R41: =Q41+R38
A42: Payback helper (months) | C42: =0 | D42: =IF(AND(C41<0,D41>=0),(D15-1+(-C41)/D38)*12,0) | E42: =IF(AND(D41<0,E41>=0),(E15-1+(-D41)/E38)*12,0) | F42: =IF(AND(E41<0,F41>=0),(F15-1+(-E41)/F38)*12,0) | G42: =IF(AND(F41<0,G41>=0),(G15-1+(-F41)/G38)*12,0) | H42: =IF(AND(G41<0,H41>=0),(H15-1+(-G41)/H38)*12,0) | I42: =IF(AND(H41<0,I41>=0),(I15-1+(-H41)/I38)*12,0) | J42: =IF(AND(I41<0,J41>=0),(J15-1+(-I41)/J38)*12,0) | K42: =IF(AND(J41<0,K41>=0),(K15-1+(-J41)/K38)*12,0) | ... R42: =IF(AND(Q41<0,R41>=0),(R15-1+(-Q41)/R38)*12,0)
A44: npv | B44: =SUM($C$40:$R$40)
A45: irr | B45: =IRR($C$38:$R$38)
A46: payback_months | B46: =IF(SUM($C$42:$R$42)=0,"n/a",SUM($C$42:$R$42))

Sheet Returns
A1: Returns, break-even and checks
A2: Illustrative and assumption-driven. Mint Velvet store-level data is not public; outputs are not Mint Velvet's store economics. Independent analysis of public filings, not affiliated with or endorsed by Mint Velvet or Sabre Retail Fashion Limited.
A4: Metric | B4: Base | C4: Downside | D4: Upside
A5: NPV (GBP) | B5: ='Store P&L'!$B$44 | C5: ='Engine'!$B$88 | D5: ='Engine'!$B$178
A6: IRR | B6: ='Store P&L'!$B$45 | C6: ='Engine'!$B$89 | D6: ='Engine'!$B$179
A7: Payback (months) | B7: ='Store P&L'!$B$46 | C7: ='Engine'!$B$90 | D7: ='Engine'!$B$180
A8: Break-even mature sales density (GBP / sq ft / yr, year-1 prices) | B8: ='Store P&L'!$B$5-'Store P&L'!$B$44*100/('Engine'!$B$43-'Store P&L'!$B$44) | C8: ='Engine'!$B$49-'Engine'!$B$88*100/('Engine'!$B$133-'Engine'!$B$88) | D8: ='Engine'!$B$139-'Engine'!$B$178*100/('Engine'!$B$223-'Engine'!$B$178)
A9: Break-even mature sales (GBP / yr, year-1 prices) | B9: =B8*area_sqft | C9: =C8*area_sqft | D9: =D8*area_sqft
A10: Assumed mature sales density | B10: ='Store P&L'!$B$5 | C10: ='Engine'!$B$49 | D10: ='Engine'!$B$139
A11: Headroom: assumed density / break-even - 1 | B11: =B10/B8-1 | C11: =C10/C8-1 | D11: =D10/D8-1
A13: Base case at maturity (year 3)
A14: Sales | B14: ='Store P&L'!$F$20
A15: Store EBITDA margin (4-wall) | B15: ='Store P&L'!$F$29/'Store P&L'!$F$20
A16: Payroll % sales | B16: ='Store P&L'!$F$23/'Store P&L'!$F$20
A17: Occupancy % sales (rent, rates, service charge) | B17: =('Store P&L'!$F$24+'Store P&L'!$F$26+'Store P&L'!$F$27)/'Store P&L'!$F$20
A19: Checks (all must be TRUE)
A20: Stock fully released by lease end | B20: =ABS(SUM('Store P&L'!$C$37:$R$37))<0.01
A21: Tax = rate x taxable profit | B21: =ABS(SUM('Store P&L'!$C$35:$R$35)-tax_rate*SUM('Store P&L'!$C$34:$R$34))<0.01
A22: FCF identity | B22: =ABS(SUM('Store P&L'!$C$38:$R$38)-(SUM('Store P&L'!$C$29:$R$29)-SUM('Store P&L'!$C$30:$R$30)-SUM('Store P&L'!$C$35:$R$35)-SUM('Store P&L'!$C$31:$R$31)-SUM('Store P&L'!$C$33:$R$33)))<0.01
A23: Downside NPV < base NPV < upside NPV | B23: =AND(C5<B5,B5<D5)
A24: IRR above discount rate exactly when NPV > 0 | B24: =(B6>discount_rate)=(B5>0)
A26: ALL CHECKS | B26: =AND(B20:B24)

Sheet Sensitivity
A1: Tornado: NPV with one driver moved +/-20% (all else base)
A2: Ramp-up speed +/-20% scales the year-1 and year-2 shortfall to maturity. A +/-20% gross-margin swing (57%-85%) is a stress, far wider than the 70.0%-71.0% product margin the FY21-FY22 filings show.
A4: Driver | B4: NPV low case | C4: NPV high case | D4: Base NPV | E4: Swing (high - low)
A5: mature_sales_density | B5: ='Engine'!$B$268 | C5: ='Engine'!$B$313 | D5: ='Store P&L'!$B$44 | E5: =C5-B5
A6: product_gross_margin | B6: ='Engine'!$B$358 | C6: ='Engine'!$B$403 | D6: ='Store P&L'!$B$44 | E6: =C6-B6
A7: rent_per_year | B7: ='Engine'!$B$448 | C7: ='Engine'!$B$493 | D7: ='Store P&L'!$B$44 | E7: =C7-B7
A8: payroll | B8: ='Engine'!$B$538 | C8: ='Engine'!$B$583 | D8: ='Store P&L'!$B$44 | E8: =C8-B8
A9: ramp_speed | B9: ='Engine'!$B$628 | C9: ='Engine'!$B$673 | D9: ='Store P&L'!$B$44 | E9: =C9-B9

Sheet Engine
A1: Engine: one full cash-flow block per case (same formulas as Store P&L)
A3: Base, density + 100 (break-even helper)
A4: param: density | B4: =mature_sales_density+100
A5: param: gm | B5: =product_gross_margin
A6: param: rent | B6: =rent_per_year
A7: param: capex | B7: =fitout_capex
A8: param: ramp1 | B8: =ramp_year1
A9: param: ramp2 | B9: =ramp_year2
A10: param: rent_mult | B10: 1
A11: param: payroll_mult | B11: 1
A12: param: ramp_mult | B12: 1
A14: Year | C14: 0 | D14: 1 | E14: 2 | F14: 3 | G14: 4 | H14: 5 | I14: 6 | J14: 7 | K14: 8 | L14: 9 | M14: 10 | N14: 11 | O14: 12 | P14: 13 | Q14: 14 | R14: 15
A15: Trading year flag | C15: =IF(AND(C14>=1,C14<=lease_term_years),1,0) | D15: =IF(AND(D14>=1,D14<=lease_term_years),1,0) | E15: =IF(AND(E14>=1,E14<=lease_term_years),1,0) | F15: =IF(AND(F14>=1,F14<=lease_term_years),1,0) | G15: =IF(AND(G14>=1,G14<=lease_term_years),1,0) | H15: =IF(AND(H14>=1,H14<=lease_term_years),1,0) | I15: =IF(AND(I14>=1,I14<=lease_term_years),1,0) | J15: =IF(AND(J14>=1,J14<=lease_term_years),1,0) | ... R15: =IF(AND(R14>=1,R14<=lease_term_years),1,0)
A16: Ramp-up (share of mature volume) | C16: =IF(C14=1,1-(1-$B$8)*$B$12,IF(C14=2,1-(1-$B$9)*$B$12,1))*C15 | D16: =IF(D14=1,1-(1-$B$8)*$B$12,IF(D14=2,1-(1-$B$9)*$B$12,1))*D15 | E16: =IF(E14=1,1-(1-$B$8)*$B$12,IF(E14=2,1-(1-$B$9)*$B$12,1))*E15 | F16: =IF(F14=1,1-(1-$B$8)*$B$12,IF(F14=2,1-(1-$B$9)*$B$12,1))*F15 | G16: =IF(G14=1,1-(1-$B$8)*$B$12,IF(G14=2,1-(1-$B$9)*$B$12,1))*G15 | H16: =IF(H14=1,1-(1-$B$8)*$B$12,IF(H14=2,1-(1-$B$9)*$B$12,1))*H15 | I16: =IF(I14=1,1-(1-$B$8)*$B$12,IF(I14=2,1-(1-$B$9)*$B$12,1))*I15 | J16: =IF(J14=1,1-(1-$B$8)*$B$12,IF(J14=2,1-(1-$B$9)*$B$12,1))*J15 | ... R16: =IF(R14=1,1-(1-$B$8)*$B$12,IF(R14=2,1-(1-$B$9)*$B$12,1))*R15
A17: Sales volume (year-1 prices) | C17: =area_sqft*$B$4*C16 | D17: =area_sqft*$B$4*D16 | E17: =area_sqft*$B$4*E16 | F17: =area_sqft*$B$4*F16 | G17: =area_sqft*$B$4*G16 | H17: =area_sqft*$B$4*H16 | I17: =area_sqft*$B$4*I16 | J17: =area_sqft*$B$4*J16 | ... R17: =area_sqft*$B$4*R16
A18: Sales growth index | C18: =IF(C15=1,(1+sales_growth)^(C14-1),0) | D18: =IF(D15=1,(1+sales_growth)^(D14-1),0) | E18: =IF(E15=1,(1+sales_growth)^(E14-1),0) | F18: =IF(F15=1,(1+sales_growth)^(F14-1),0) | G18: =IF(G15=1,(1+sales_growth)^(G14-1),0) | H18: =IF(H15=1,(1+sales_growth)^(H14-1),0) | I18: =IF(I15=1,(1+sales_growth)^(I14-1),0) | J18: =IF(J15=1,(1+sales_growth)^(J14-1),0) | ... R18: =IF(R15=1,(1+sales_growth)^(R14-1),0)
A19: Sales | C19: =C17*C18 | D19: =D17*D18 | E19: =E17*E18 | F19: =F17*F18 | G19: =G17*G18 | H19: =H17*H18 | I19: =I17*I18 | J19: =J17*J18 | ... R19: =R17*R18
A20: Gross margin | C20: =C19*$B$5 | D20: =D19*$B$5 | E20: =E19*$B$5 | F20: =F19*$B$5 | G20: =G19*$B$5 | H20: =H19*$B$5 | I20: =I19*$B$5 | J20: =J19*$B$5 | ... R20: =R19*$B$5
A21: Wage index | C21: =IF(C15=1,(1+wage_inflation)^(C14-1),0) | D21: =IF(D15=1,(1+wage_inflation)^(D14-1),0) | E21: =IF(E15=1,(1+wage_inflation)^(E14-1),0) | F21: =IF(F15=1,(1+wage_inflation)^(F14-1),0) | G21: =IF(G15=1,(1+wage_inflation)^(G14-1),0) | H21: =IF(H15=1,(1+wage_inflation)^(H14-1),0) | I21: =IF(I15=1,(1+wage_inflation)^(I14-1),0) | J21: =IF(J15=1,(1+wage_inflation)^(J14-1),0) | ... R21: =IF(R15=1,(1+wage_inflation)^(R14-1),0)
A22: Payroll | C22: =(fixed_payroll*C15+variable_cost_per_k*C17/1000)*C21*$B$11 | D22: =(fixed_payroll*D15+variable_cost_per_k*D17/1000)*D21*$B$11 | E22: =(fixed_payroll*E15+variable_cost_per_k*E17/1000)*E21*$B$11 | F22: =(fixed_payroll*F15+variable_cost_per_k*F17/1000)*F21*$B$11 | G22: =(fixed_payroll*G15+variable_cost_per_k*G17/1000)*G21*$B$11 | H22: =(fixed_payroll*H15+variable_cost_per_k*H17/1000)*H21*$B$11 | I22: =(fixed_payroll*I15+variable_cost_per_k*I17/1000)*I21*$B$11 | J22: =(fixed_payroll*J15+variable_cost_per_k*J17/1000)*J21*$B$11 | ... R22: =(fixed_payroll*R15+variable_cost_per_k*R17/1000)*R21*$B$11
A23: Rent | C23: =$B$6*(1+IF(C14>=6,rent_review_uplift,0))*C15*$B$10 | D23: =$B$6*(1+IF(D14>=6,rent_review_uplift,0))*D15*$B$10 | E23: =$B$6*(1+IF(E14>=6,rent_review_uplift,0))*E15*$B$10 | F23: =$B$6*(1+IF(F14>=6,rent_review_uplift,0))*F15*$B$10 | G23: =$B$6*(1+IF(G14>=6,rent_review_uplift,0))*G15*$B$10 | H23: =$B$6*(1+IF(H14>=6,rent_review_uplift,0))*H15*$B$10 | I23: =$B$6*(1+IF(I14>=6,rent_review_uplift,0))*I15*$B$10 | J23: =$B$6*(1+IF(J14>=6,rent_review_uplift,0))*J15*$B$10 | ... R23: =$B$6*(1+IF(R14>=6,rent_review_uplift,0))*R15*$B$10
A24: Cost index | C24: =IF(C15=1,(1+cost_inflation)^(C14-1),0) | D24: =IF(D15=1,(1+cost_inflation)^(D14-1),0) | E24: =IF(E15=1,(1+cost_inflation)^(E14-1),0) | F24: =IF(F15=1,(1+cost_inflation)^(F14-1),0) | G24: =IF(G15=1,(1+cost_inflation)^(G14-1),0) | H24: =IF(H15=1,(1+cost_inflation)^(H14-1),0) | I24: =IF(I15=1,(1+cost_inflation)^(I14-1),0) | J24: =IF(J15=1,(1+cost_inflation)^(J14-1),0) | ... R24: =IF(R15=1,(1+cost_inflation)^(R14-1),0)
A25: Business rates | C25: =rateable_value*IF(rateable_value<51000,rates_multiplier_rhl_small,IF(rateable_value<500000,rates_multiplier_rhl_standard,rates_multiplier_high_value))*C24 | D25: =rateable_value*IF(rateable_value<51000,rates_multiplier_rhl_small,IF(rateable_value<500000,rates_multiplier_rhl_standard,rates_multiplier_high_value))*D24 | E25: =rateable_value*IF(rateable_value<51000,rates_multiplier_rhl_small,IF(rateable_value<500000,rates_multiplier_rhl_standard,rates_multiplier_high_value))*E24 | F25: =rateable_value*IF(rateable_value<51000,rates_multiplier_rhl_small,IF(rateable_value<500000,rates_multiplier_rhl_standard,rates_multiplier_high_value))*F24 | G25: =rateable_value*IF(rateable_value<51000,rates_multiplier_rhl_small,IF(rateable_value<500000,rates_multiplier_rhl_standard,rates_multiplier_high_value))*G24 | H25: =rateable_value*IF(rateable_value<51000,rates_multiplier_rhl_small,IF(rateable_value<500000,rates_multiplier_rhl_standard,rates_multiplier_high_value))*H24 | I25: =rateable_value*IF(rateable_value<51000,rates_multiplier_rhl_small,IF(rateable_value<500000,rates_multiplier_rhl_standard,rates_multiplier_high_value))*I24 | J25: =rateable_value*IF(rateable_value<51000,rates_multiplier_rhl_small,IF(rateable_value<500000,rates_multiplier_rhl_standard,rates_multiplier_high_value))*J24 | ... R25: =rateable_value*IF(rateable_value<51000,rates_multiplier_rhl_small,IF(rateable_value<500000,rates_multiplier_rhl_standard,rates_multiplier_high_value))*R24
A26: Service charge, utilities, insurance | C26: =occupancy_other_psf*area_sqft*C24 | D26: =occupancy_other_psf*area_sqft*D24 | E26: =occupancy_other_psf*area_sqft*E24 | F26: =occupancy_other_psf*area_sqft*F24 | G26: =occupancy_other_psf*area_sqft*G24 | H26: =occupancy_other_psf*area_sqft*H24 | I26: =occupancy_other_psf*area_sqft*I24 | J26: =occupancy_other_psf*area_sqft*J24 | ... R26: =occupancy_other_psf*area_sqft*R24
A27: Other store opex | C27: =C19*other_opex_pct_sales | D27: =D19*other_opex_pct_sales | E27: =E19*other_opex_pct_sales | F27: =F19*other_opex_pct_sales | G27: =G19*other_opex_pct_sales | H27: =H19*other_opex_pct_sales | I27: =I19*other_opex_pct_sales | J27: =J19*other_opex_pct_sales | ... R27: =R19*other_opex_pct_sales
A28: Store EBITDA (4-wall) | C28: =C20-C22-C23-C25-C26-C27 | D28: =D20-D22-D23-D25-D26-D27 | E28: =E20-E22-E23-E25-E26-E27 | F28: =F20-F22-F23-F25-F26-F27 | G28: =G20-G22-G23-G25-G26-G27 | H28: =H20-H22-H23-H25-H26-H27 | I28: =I20-I22-I23-I25-I26-I27 | J28: =J20-J22-J23-J25-J26-J27 | ... R28: =R20-R22-R23-R25-R26-R27
A29: Pre-opening costs | C29: =IF(C14=0,pre_opening_costs,0) | D29: =IF(D14=0,pre_opening_costs,0) | E29: =IF(E14=0,pre_opening_costs,0) | F29: =IF(F14=0,pre_opening_costs,0) | G29: =IF(G14=0,pre_opening_costs,0) | H29: =IF(H14=0,pre_opening_costs,0) | I29: =IF(I14=0,pre_opening_costs,0) | J29: =IF(J14=0,pre_opening_costs,0) | ... R29: =IF(R14=0,pre_opening_costs,0)
A30: Fit-out capex | C30: =IF(C14=0,$B$7,0) | D30: =IF(D14=0,$B$7,0) | E30: =IF(E14=0,$B$7,0) | F30: =IF(F14=0,$B$7,0) | G30: =IF(G14=0,$B$7,0) | H30: =IF(H14=0,$B$7,0) | I30: =IF(I14=0,$B$7,0) | J30: =IF(J14=0,$B$7,0) | ... R30: =IF(R14=0,$B$7,0)
A31: Tax depreciation | C31: =IF(AND(C14>=1,C14<=tax_depreciation_years,C14<=lease_term_years),$B$7/tax_depreciation_years,0) | D31: =IF(AND(D14>=1,D14<=tax_depreciation_years,D14<=lease_term_years),$B$7/tax_depreciation_years,0) | E31: =IF(AND(E14>=1,E14<=tax_depreciation_years,E14<=lease_term_years),$B$7/tax_depreciation_years,0) | F31: =IF(AND(F14>=1,F14<=tax_depreciation_years,F14<=lease_term_years),$B$7/tax_depreciation_years,0) | G31: =IF(AND(G14>=1,G14<=tax_depreciation_years,G14<=lease_term_years),$B$7/tax_depreciation_years,0) | H31: =IF(AND(H14>=1,H14<=tax_depreciation_years,H14<=lease_term_years),$B$7/tax_depreciation_years,0) | I31: =IF(AND(I14>=1,I14<=tax_depreciation_years,I14<=lease_term_years),$B$7/tax_depreciation_years,0) | J31: =IF(AND(J14>=1,J14<=tax_depreciation_years,J14<=lease_term_years),$B$7/tax_depreciation_years,0) | ... R31: =IF(AND(R14>=1,R14<=tax_depreciation_years,R14<=lease_term_years),$B$7/tax_depreciation_years,0)
A32: Dilapidations | C32: =IF(C14=lease_term_years,dilapidations_at_exit,0) | D32: =IF(D14=lease_term_years,dilapidations_at_exit,0) | E32: =IF(E14=lease_term_years,dilapidations_at_exit,0) | F32: =IF(F14=lease_term_years,dilapidations_at_exit,0) | G32: =IF(G14=lease_term_years,dilapidations_at_exit,0) | H32: =IF(H14=lease_term_years,dilapidations_at_exit,0) | I32: =IF(I14=lease_term_years,dilapidations_at_exit,0) | J32: =IF(J14=lease_term_years,dilapidations_at_exit,0) | ... R32: =IF(R14=lease_term_years,dilapidations_at_exit,0)
A33: Taxable profit | C33: =C28-C29-C31-C32 | D33: =D28-D29-D31-D32 | E33: =E28-E29-E31-E32 | F33: =F28-F29-F31-F32 | G33: =G28-G29-G31-G32 | H33: =H28-H29-H31-H32 | I33: =I28-I29-I31-I32 | J33: =J28-J29-J31-J32 | ... R33: =R28-R29-R31-R32
A34: Tax (negative = group relief) | C34: =C33*tax_rate | D34: =D33*tax_rate | E34: =E33*tax_rate | F34: =F33*tax_rate | G34: =G33*tax_rate | H34: =H33*tax_rate | I34: =I33*tax_rate | J34: =J33*tax_rate | ... R34: =R33*tax_rate
A35: Stock held | C35: =IF(C14<lease_term_years,stock_pct_sales*D19,0) | D35: =IF(D14<lease_term_years,stock_pct_sales*E19,0) | E35: =IF(E14<lease_term_years,stock_pct_sales*F19,0) | F35: =IF(F14<lease_term_years,stock_pct_sales*G19,0) | G35: =IF(G14<lease_term_years,stock_pct_sales*H19,0) | H35: =IF(H14<lease_term_years,stock_pct_sales*I19,0) | I35: =IF(I14<lease_term_years,stock_pct_sales*J19,0) | J35: =IF(J14<lease_term_years,stock_pct_sales*K19,0) | ... Q35: =IF(Q14<lease_term_years,stock_pct_sales*R19,0) | R35: =0
A36: Change in stock | C36: =C35 | D36: =D35-C35 | E36: =E35-D35 | F36: =F35-E35 | G36: =G35-F35 | H36: =H35-G35 | I36: =I35-H35 | J36: =J35-I35 | K36: =K35-J35 | ... R36: =R35-Q35
A37: Free cash flow | C37: =C28-C29-C34-C30-C36-C32 | D37: =D28-D29-D34-D30-D36-D32 | E37: =E28-E29-E34-E30-E36-E32 | F37: =F28-F29-F34-F30-F36-F32 | G37: =G28-G29-G34-G30-G36-G32 | H37: =H28-H29-H34-H30-H36-H32 | I37: =I28-I29-I34-I30-I36-I32 | J37: =J28-J29-J34-J30-J36-J32 | ... R37: =R28-R29-R34-R30-R36-R32
A38: Discount factor | C38: =1/(1+discount_rate)^C14 | D38: =1/(1+discount_rate)^D14 | E38: =1/(1+discount_rate)^E14 | F38: =1/(1+discount_rate)^F14 | G38: =1/(1+discount_rate)^G14 | H38: =1/(1+discount_rate)^H14 | I38: =1/(1+discount_rate)^I14 | J38: =1/(1+discount_rate)^J14 | ... R38: =1/(1+discount_rate)^R14
A39: Present value | C39: =C37*C38 | D39: =D37*D38 | E39: =E37*E38 | F39: =F37*F38 | G39: =G37*G38 | H39: =H37*H38 | I39: =I37*I38 | J39: =J37*J38 | ... R39: =R37*R38
A40: Cumulative cash flow | C40: =C37 | D40: =C40+D37 | E40: =D40+E37 | F40: =E40+F37 | G40: =F40+G37 | H40: =G40+H37 | I40: =H40+I37 | J40: =I40+J37 | K40: =J40+K37 | ... R40: =Q40+R37
A41: Payback helper (months) | C41: =0 | D41: =IF(AND(C40<0,D40>=0),(D14-1+(-C40)/D37)*12,0) | E41: =IF(AND(D40<0,E40>=0),(E14-1+(-D40)/E37)*12,0) | F41: =IF(AND(E40<0,F40>=0),(F14-1+(-E40)/F37)*12,0) | G41: =IF(AND(F40<0,G40>=0),(G14-1+(-F40)/G37)*12,0) | H41: =IF(AND(G40<0,H40>=0),(H14-1+(-G40)/H37)*12,0) | I41: =IF(AND(H40<0,I40>=0),(I14-1+(-H40)/I37)*12,0) | J41: =IF(AND(I40<0,J40>=0),(J14-1+(-I40)/J37)*12,0) | K41: =IF(AND(J40<0,K40>=0),(K14-1+(-J40)/K37)*12,0) | ... R41: =IF(AND(Q40<0,R40>=0),(R14-1+(-Q40)/R37)*12,0)
A43: npv | B43: =SUM($C$39:$R$39)
A44: irr | B44: =IRR($C$37:$R$37)
A45: payback_months | B45: =IF(SUM($C$41:$R$41)=0,"n/a",SUM($C$41:$R$41))
A48: Scenario: downside
A49: param: density | B49: =mature_sales_density_low
A50: param: gm | B50: =product_gross_margin_low
A51: param: rent | B51: =rent_per_year_high
A52: param: capex | B52: =fitout_capex_high
A53: param: ramp1 | B53: =ramp_year1_low
A54: param: ramp2 | B54: =ramp_year2_low
A55: param: rent_mult | B55: 1
A56: param: payroll_mult | B56: 1
A57: param: ramp_mult | B57: 1
A59: Year | C59: 0 | D59: 1 | E59: 2 | F59: 3 | G59: 4 | H59: 5 | I59: 6 | J59: 7 | K59: 8 | L59: 9 | M59: 10 | N59: 11 | O59: 12 | P59: 13 | Q59: 14 | R59: 15
A60: Trading year flag | C60: =IF(AND(C59>=1,C59<=lease_term_years),1,0) | D60: =IF(AND(D59>=1,D59<=lease_term_years),1,0) | E60: =IF(AND(E59>=1,E59<=lease_term_years),1,0) | F60: =IF(AND(F59>=1,F59<=lease_term_years),1,0) | G60: =IF(AND(G59>=1,G59<=lease_term_years),1,0) | H60: =IF(AND(H59>=1,H59<=lease_term_years),1,0) | I60: =IF(AND(I59>=1,I59<=lease_term_years),1,0) | J60: =IF(AND(J59>=1,J59<=lease_term_years),1,0) | ... R60: =IF(AND(R59>=1,R59<=lease_term_years),1,0)
A61: Ramp-up (share of mature volume) | C61: =IF(C59=1,1-(1-$B$53)*$B$57,IF(C59=2,1-(1-$B$54)*$B$57,1))*C60 | D61: =IF(D59=1,1-(1-$B$53)*$B$57,IF(D59=2,1-(1-$B$54)*$B$57,1))*D60 | E61: =IF(E59=1,1-(1-$B$53)*$B$57,IF(E59=2,1-(1-$B$54)*$B$57,1))*E60 | F61: =IF(F59=1,1-(1-$B$53)*$B$57,IF(F59=2,1-(1-$B$54)*$B$57,1))*F60 | G61: =IF(G59=1,1-(1-$B$53)*$B$57,IF(G59=2,1-(1-$B$54)*$B$57,1))*G60 | H61: =IF(H59=1,1-(1-$B$53)*$B$57,IF(H59=2,1-(1-$B$54)*$B$57,1))*H60 | I61: =IF(I59=1,1-(1-$B$53)*$B$57,IF(I59=2,1-(1-$B$54)*$B$57,1))*I60 | J61: =IF(J59=1,1-(1-$B$53)*$B$57,IF(J59=2,1-(1-$B$54)*$B$57,1))*J60 | ... R61: =IF(R59=1,1-(1-$B$53)*$B$57,IF(R59=2,1-(1-$B$54)*$B$57,1))*R60
A62: Sales volume (year-1 prices) | C62: =area_sqft*$B$49*C61 | D62: =area_sqft*$B$49*D61 | E62: =area_sqft*$B$49*E61 | F62: =area_sqft*$B$49*F61 | G62: =area_sqft*$B$49*G61 | H62: =area_sqft*$B$49*H61 | I62: =area_sqft*$B$49*I61 | J62: =area_sqft*$B$49*J61 | ... R62: =area_sqft*$B$49*R61
A63: Sales growth index | C63: =IF(C60=1,(1+sales_growth)^(C59-1),0) | D63: =IF(D60=1,(1+sales_growth)^(D59-1),0) | E63: =IF(E60=1,(1+sales_growth)^(E59-1),0) | F63: =IF(F60=1,(1+sales_growth)^(F59-1),0) | G63: =IF(G60=1,(1+sales_growth)^(G59-1),0) | H63: =IF(H60=1,(1+sales_growth)^(H59-1),0) | I63: =IF(I60=1,(1+sales_growth)^(I59-1),0) | J63: =IF(J60=1,(1+sales_growth)^(J59-1),0) | ... R63: =IF(R60=1,(1+sales_growth)^(R59-1),0)
A64: Sales | C64: =C62*C63 | D64: =D62*D63 | E64: =E62*E63 | F64: =F62*F63 | G64: =G62*G63 | H64: =H62*H63 | I64: =I62*I63 | J64: =J62*J63 | ... R64: =R62*R63
A65: Gross margin | C65: =C64*$B$50 | D65: =D64*$B$50 | E65: =E64*$B$50 | F65: =F64*$B$50 | G65: =G64*$B$50 | H65: =H64*$B$50 | I65: =I64*$B$50 | J65: =J64*$B$50 | ... R65: =R64*$B$50
A66: Wage index | C66: =IF(C60=1,(1+wage_inflation)^(C59-1),0) | D66: =IF(D60=1,(1+wage_inflation)^(D59-1),0) | E66: =IF(E60=1,(1+wage_inflation)^(E59-1),0) | F66: =IF(F60=1,(1+wage_inflation)^(F59-1),0) | G66: =IF(G60=1,(1+wage_inflation)^(G59-1),0) | H66: =IF(H60=1,(1+wage_inflation)^(H59-1),0) | I66: =IF(I60=1,(1+wage_inflation)^(I59-1),0) | J66: =IF(J60=1,(1+wage_inflation)^(J59-1),0) | ... R66: =IF(R60=1,(1+wage_inflation)^(R59-1),0)
A67: Payroll | C67: =(fixed_payroll*C60+variable_cost_per_k*C62/1000)*C66*$B$56 | D67: =(fixed_payroll*D60+variable_cost_per_k*D62/1000)*D66*$B$56 | E67: =(fixed_payroll*E60+variable_cost_per_k*E62/1000)*E66*$B$56 | F67: =(fixed_payroll*F60+variable_cost_per_k*F62/1000)*F66*$B$56 | G67: =(fixed_payroll*G60+variable_cost_per_k*G62/1000)*G66*$B$56 | H67: =(fixed_payroll*H60+variable_cost_per_k*H62/1000)*H66*$B$56 | I67: =(fixed_payroll*I60+variable_cost_per_k*I62/1000)*I66*$B$56 | J67: =(fixed_payroll*J60+variable_cost_per_k*J62/1000)*J66*$B$56 | ... R67: =(fixed_payroll*R60+variable_cost_per_k*R62/1000)*R66*$B$56
A68: Rent | C68: =$B$51*(1+IF(C59>=6,rent_review_uplift,0))*C60*$B$55 | D68: =$B$51*(1+IF(D59>=6,rent_review_uplift,0))*D60*$B$55 | E68: =$B$51*(1+IF(E59>=6,rent_review_uplift,0))*E60*$B$55 | F68: =$B$51*(1+IF(F59>=6,rent_review_uplift,0))*F60*$B$55 | G68: =$B$51*(1+IF(G59>=6,rent_review_uplift,0))*G60*$B$55 | H68: =$B$51*(1+IF(H59>=6,rent_review_uplift,0))*H60*$B$55 | I68: =$B$51*(1+IF(I59>=6,rent_review_uplift,0))*I60*$B$55 | J68: =$B$51*(1+IF(J59>=6,rent_review_uplift,0))*J60*$B$55 | ... R68: =$B$51*(1+IF(R59>=6,rent_review_uplift,0))*R60*$B$55
A69: Cost index | C69: =IF(C60=1,(1+cost_inflation)^(C59-1),0) | D69: =IF(D60=1,(1+cost_inflation)^(D59-1),0) | E69: =IF(E60=1,(1+cost_inflation)^(E59-1),0) | F69: =IF(F60=1,(1+cost_inflation)^(F59-1),0) | G69: =IF(G60=1,(1+cost_inflation)^(G59-1),0) | H69: =IF(H60=1,(1+cost_inflation)^(H59-1),0) | I69: =IF(I60=1,(1+cost_inflation)^(I59-1),0) | J69: =IF(J60=1,(1+cost_inflation)^(J59-1),0) | ... R69: =IF(R60=1,(1+cost_inflation)^(R59-1),0)
A70: Business rates | C70: =rateable_value*IF(rateable_value<51000,rates_multiplier_rhl_small,IF(rateable_value<500000,rates_multiplier_rhl_standard,rates_multiplier_high_value))*C69 | D70: =rateable_value*IF(rateable_value<51000,rates_multiplier_rhl_small,IF(rateable_value<500000,rates_multiplier_rhl_standard,rates_multiplier_high_value))*D69 | E70: =rateable_value*IF(rateable_value<51000,rates_multiplier_rhl_small,IF(rateable_value<500000,rates_multiplier_rhl_standard,rates_multiplier_high_value))*E69 | F70: =rateable_value*IF(rateable_value<51000,rates_multiplier_rhl_small,IF(rateable_value<500000,rates_multiplier_rhl_standard,rates_multiplier_high_value))*F69 | G70: =rateable_value*IF(rateable_value<51000,rates_multiplier_rhl_small,IF(rateable_value<500000,rates_multiplier_rhl_standard,rates_multiplier_high_value))*G69 | H70: =rateable_value*IF(rateable_value<51000,rates_multiplier_rhl_small,IF(rateable_value<500000,rates_multiplier_rhl_standard,rates_multiplier_high_value))*H69 | I70: =rateable_value*IF(rateable_value<51000,rates_multiplier_rhl_small,IF(rateable_value<500000,rates_multiplier_rhl_standard,rates_multiplier_high_value))*I69 | J70: =rateable_value*IF(rateable_value<51000,rates_multiplier_rhl_small,IF(rateable_value<500000,rates_multiplier_rhl_standard,rates_multiplier_high_value))*J69 | ... R70: =rateable_value*IF(rateable_value<51000,rates_multiplier_rhl_small,IF(rateable_value<500000,rates_multiplier_rhl_standard,rates_multiplier_high_value))*R69
A71: Service charge, utilities, insurance | C71: =occupancy_other_psf*area_sqft*C69 | D71: =occupancy_other_psf*area_sqft*D69 | E71: =occupancy_other_psf*area_sqft*E69 | F71: =occupancy_other_psf*area_sqft*F69 | G71: =occupancy_other_psf*area_sqft*G69 | H71: =occupancy_other_psf*area_sqft*H69 | I71: =occupancy_other_psf*area_sqft*I69 | J71: =occupancy_other_psf*area_sqft*J69 | ... R71: =occupancy_other_psf*area_sqft*R69
A72: Other store opex | C72: =C64*other_opex_pct_sales | D72: =D64*other_opex_pct_sales | E72: =E64*other_opex_pct_sales | F72: =F64*other_opex_pct_sales | G72: =G64*other_opex_pct_sales | H72: =H64*other_opex_pct_sales | I72: =I64*other_opex_pct_sales | J72: =J64*other_opex_pct_sales | ... R72: =R64*other_opex_pct_sales
A73: Store EBITDA (4-wall) | C73: =C65-C67-C68-C70-C71-C72 | D73: =D65-D67-D68-D70-D71-D72 | E73: =E65-E67-E68-E70-E71-E72 | F73: =F65-F67-F68-F70-F71-F72 | G73: =G65-G67-G68-G70-G71-G72 | H73: =H65-H67-H68-H70-H71-H72 | I73: =I65-I67-I68-I70-I71-I72 | J73: =J65-J67-J68-J70-J71-J72 | ... R73: =R65-R67-R68-R70-R71-R72
A74: Pre-opening costs | C74: =IF(C59=0,pre_opening_costs,0) | D74: =IF(D59=0,pre_opening_costs,0) | E74: =IF(E59=0,pre_opening_costs,0) | F74: =IF(F59=0,pre_opening_costs,0) | G74: =IF(G59=0,pre_opening_costs,0) | H74: =IF(H59=0,pre_opening_costs,0) | I74: =IF(I59=0,pre_opening_costs,0) | J74: =IF(J59=0,pre_opening_costs,0) | ... R74: =IF(R59=0,pre_opening_costs,0)
A75: Fit-out capex | C75: =IF(C59=0,$B$52,0) | D75: =IF(D59=0,$B$52,0) | E75: =IF(E59=0,$B$52,0) | F75: =IF(F59=0,$B$52,0) | G75: =IF(G59=0,$B$52,0) | H75: =IF(H59=0,$B$52,0) | I75: =IF(I59=0,$B$52,0) | J75: =IF(J59=0,$B$52,0) | ... R75: =IF(R59=0,$B$52,0)
A76: Tax depreciation | C76: =IF(AND(C59>=1,C59<=tax_depreciation_years,C59<=lease_term_years),$B$52/tax_depreciation_years,0) | D76: =IF(AND(D59>=1,D59<=tax_depreciation_years,D59<=lease_term_years),$B$52/tax_depreciation_years,0) | E76: =IF(AND(E59>=1,E59<=tax_depreciation_years,E59<=lease_term_years),$B$52/tax_depreciation_years,0) | F76: =IF(AND(F59>=1,F59<=tax_depreciation_years,F59<=lease_term_years),$B$52/tax_depreciation_years,0) | G76: =IF(AND(G59>=1,G59<=tax_depreciation_years,G59<=lease_term_years),$B$52/tax_depreciation_years,0) | H76: =IF(AND(H59>=1,H59<=tax_depreciation_years,H59<=lease_term_years),$B$52/tax_depreciation_years,0) | I76: =IF(AND(I59>=1,I59<=tax_depreciation_years,I59<=lease_term_years),$B$52/tax_depreciation_years,0) | J76: =IF(AND(J59>=1,J59<=tax_depreciation_years,J59<=lease_term_years),$B$52/tax_depreciation_years,0) | ... R76: =IF(AND(R59>=1,R59<=tax_depreciation_years,R59<=lease_term_years),$B$52/tax_depreciation_years,0)
A77: Dilapidations | C77: =IF(C59=lease_term_years,dilapidations_at_exit,0) | D77: =IF(D59=lease_term_years,dilapidations_at_exit,0) | E77: =IF(E59=lease_term_years,dilapidations_at_exit,0) | F77: =IF(F59=lease_term_years,dilapidations_at_exit,0) | G77: =IF(G59=lease_term_years,dilapidations_at_exit,0) | H77: =IF(H59=lease_term_years,dilapidations_at_exit,0) | I77: =IF(I59=lease_term_years,dilapidations_at_exit,0) | J77: =IF(J59=lease_term_years,dilapidations_at_exit,0) | ... R77: =IF(R59=lease_term_years,dilapidations_at_exit,0)
A78: Taxable profit | C78: =C73-C74-C76-C77 | D78: =D73-D74-D76-D77 | E78: =E73-E74-E76-E77 | F78: =F73-F74-F76-F77 | G78: =G73-G74-G76-G77 | H78: =H73-H74-H76-H77 | I78: =I73-I74-I76-I77 | J78: =J73-J74-J76-J77 | ... R78: =R73-R74-R76-R77
A79: Tax (negative = group relief) | C79: =C78*tax_rate | D79: =D78*tax_rate | E79: =E78*tax_rate | F79: =F78*tax_rate | G79: =G78*tax_rate | H79: =H78*tax_rate | I79: =I78*tax_rate | J79: =J78*tax_rate | ... R79: =R78*tax_rate
A80: Stock held | C80: =IF(C59<lease_term_years,stock_pct_sales*D64,0) | D80: =IF(D59<lease_term_years,stock_pct_sales*E64,0) | E80: =IF(E59<lease_term_years,stock_pct_sales*F64,0) | F80: =IF(F59<lease_term_years,stock_pct_sales*G64,0) | G80: =IF(G59<lease_term_years,stock_pct_sales*H64,0) | H80: =IF(H59<lease_term_years,stock_pct_sales*I64,0) | I80: =IF(I59<lease_term_years,stock_pct_sales*J64,0) | J80: =IF(J59<lease_term_years,stock_pct_sales*K64,0) | ... Q80: =IF(Q59<lease_term_years,stock_pct_sales*R64,0) | R80: =0
A81: Change in stock | C81: =C80 | D81: =D80-C80 | E81: =E80-D80 | F81: =F80-E80 | G81: =G80-F80 | H81: =H80-G80 | I81: =I80-H80 | J81: =J80-I80 | K81: =K80-J80 | ... R81: =R80-Q80
A82: Free cash flow | C82: =C73-C74-C79-C75-C81-C77 | D82: =D73-D74-D79-D75-D81-D77 | E82: =E73-E74-E79-E75-E81-E77 | F82: =F73-F74-F79-F75-F81-F77 | G82: =G73-G74-G79-G75-G81-G77 | H82: =H73-H74-H79-H75-H81-H77 | I82: =I73-I74-I79-I75-I81-I77 | J82: =J73-J74-J79-J75-J81-J77 | ... R82: =R73-R74-R79-R75-R81-R77
A83: Discount factor | C83: =1/(1+discount_rate)^C59 | D83: =1/(1+discount_rate)^D59 | E83: =1/(1+discount_rate)^E59 | F83: =1/(1+discount_rate)^F59 | G83: =1/(1+discount_rate)^G59 | H83: =1/(1+discount_rate)^H59 | I83: =1/(1+discount_rate)^I59 | J83: =1/(1+discount_rate)^J59 | ... R83: =1/(1+discount_rate)^R59
A84: Present value | C84: =C82*C83 | D84: =D82*D83 | E84: =E82*E83 | F84: =F82*F83 | G84: =G82*G83 | H84: =H82*H83 | I84: =I82*I83 | J84: =J82*J83 | ... R84: =R82*R83
A85: Cumulative cash flow | C85: =C82 | D85: =C85+D82 | E85: =D85+E82 | F85: =E85+F82 | G85: =F85+G82 | H85: =G85+H82 | I85: =H85+I82 | J85: =I85+J82 | K85: =J85+K82 | ... R85: =Q85+R82
A86: Payback helper (months) | C86: =0 | D86: =IF(AND(C85<0,D85>=0),(D59-1+(-C85)/D82)*12,0) | E86: =IF(AND(D85<0,E85>=0),(E59-1+(-D85)/E82)*12,0) | F86: =IF(AND(E85<0,F85>=0),(F59-1+(-E85)/F82)*12,0) | G86: =IF(AND(F85<0,G85>=0),(G59-1+(-F85)/G82)*12,0) | H86: =IF(AND(G85<0,H85>=0),(H59-1+(-G85)/H82)*12,0) | I86: =IF(AND(H85<0,I85>=0),(I59-1+(-H85)/I82)*12,0) | J86: =IF(AND(I85<0,J85>=0),(J59-1+(-I85)/J82)*12,0) | K86: =IF(AND(J85<0,K85>=0),(K59-1+(-J85)/K82)*12,0) | ... R86: =IF(AND(Q85<0,R85>=0),(R59-1+(-Q85)/R82)*12,0)
A88: npv | B88: =SUM($C$84:$R$84)
A89: irr | B89: =IRR($C$82:$R$82)
A90: payback_months | B90: =IF(SUM($C$86:$R$86)=0,"n/a",SUM($C$86:$R$86))
A93: Scenario: downside, density + 100
A94: param: density | B94: =mature_sales_density_low+100
A95: param: gm | B95: =product_gross_margin_low
A96: param: rent | B96: =rent_per_year_high
A97: param: capex | B97: =fitout_capex_high
A98: param: ramp1 | B98: =ramp_year1_low
A99: param: ramp2 | B99: =ramp_year2_low
A100: param: rent_mult | B100: 1
A101: param: payroll_mult | B101: 1
A102: param: ramp_mult | B102: 1
A104: Year | C104: 0 | D104: 1 | E104: 2 | F104: 3 | G104: 4 | H104: 5 | I104: 6 | J104: 7 | K104: 8 | L104: 9 | M104: 10 | N104: 11 | O104: 12 | P104: 13 | Q104: 14 | R104: 15
A105: Trading year flag | C105: =IF(AND(C104>=1,C104<=lease_term_years),1,0) | D105: =IF(AND(D104>=1,D104<=lease_term_years),1,0) | E105: =IF(AND(E104>=1,E104<=lease_term_years),1,0) | F105: =IF(AND(F104>=1,F104<=lease_term_years),1,0) | G105: =IF(AND(G104>=1,G104<=lease_term_years),1,0) | H105: =IF(AND(H104>=1,H104<=lease_term_years),1,0) | I105: =IF(AND(I104>=1,I104<=lease_term_years),1,0) | J105: =IF(AND(J104>=1,J104<=lease_term_years),1,0) | ... R105: =IF(AND(R104>=1,R104<=lease_term_years),1,0)
A106: Ramp-up (share of mature volume) | C106: =IF(C104=1,1-(1-$B$98)*$B$102,IF(C104=2,1-(1-$B$99)*$B$102,1))*C105 | D106: =IF(D104=1,1-(1-$B$98)*$B$102,IF(D104=2,1-(1-$B$99)*$B$102,1))*D105 | E106: =IF(E104=1,1-(1-$B$98)*$B$102,IF(E104=2,1-(1-$B$99)*$B$102,1))*E105 | F106: =IF(F104=1,1-(1-$B$98)*$B$102,IF(F104=2,1-(1-$B$99)*$B$102,1))*F105 | G106: =IF(G104=1,1-(1-$B$98)*$B$102,IF(G104=2,1-(1-$B$99)*$B$102,1))*G105 | H106: =IF(H104=1,1-(1-$B$98)*$B$102,IF(H104=2,1-(1-$B$99)*$B$102,1))*H105 | I106: =IF(I104=1,1-(1-$B$98)*$B$102,IF(I104=2,1-(1-$B$99)*$B$102,1))*I105 | J106: =IF(J104=1,1-(1-$B$98)*$B$102,IF(J104=2,1-(1-$B$99)*$B$102,1))*J105 | ... R106: =IF(R104=1,1-(1-$B$98)*$B$102,IF(R104=2,1-(1-$B$99)*$B$102,1))*R105
A107: Sales volume (year-1 prices) | C107: =area_sqft*$B$94*C106 | D107: =area_sqft*$B$94*D106 | E107: =area_sqft*$B$94*E106 | F107: =area_sqft*$B$94*F106 | G107: =area_sqft*$B$94*G106 | H107: =area_sqft*$B$94*H106 | I107: =area_sqft*$B$94*I106 | J107: =area_sqft*$B$94*J106 | ... R107: =area_sqft*$B$94*R106
A108: Sales growth index | C108: =IF(C105=1,(1+sales_growth)^(C104-1),0) | D108: =IF(D105=1,(1+sales_growth)^(D104-1),0) | E108: =IF(E105=1,(1+sales_growth)^(E104-1),0) | F108: =IF(F105=1,(1+sales_growth)^(F104-1),0) | G108: =IF(G105=1,(1+sales_growth)^(G104-1),0) | H108: =IF(H105=1,(1+sales_growth)^(H104-1),0) | I108: =IF(I105=1,(1+sales_growth)^(I104-1),0) | J108: =IF(J105=1,(1+sales_growth)^(J104-1),0) | ... R108: =IF(R105=1,(1+sales_growth)^(R104-1),0)
A109: Sales | C109: =C107*C108 | D109: =D107*D108 | E109: =E107*E108 | F109: =F107*F108 | G109: =G107*G108 | H109: =H107*H108 | I109: =I107*I108 | J109: =J107*J108 | ... R109: =R107*R108
A110: Gross margin | C110: =C109*$B$95 | D110: =D109*$B$95 | E110: =E109*$B$95 | F110: =F109*$B$95 | G110: =G109*$B$95 | H110: =H109*$B$95 | I110: =I109*$B$95 | J110: =J109*$B$95 | ... R110: =R109*$B$95
...
